tnp/__init__.py
tnp/data/__init__.py
tnp/data/base.py
tnp/data/gp.py
tnp/data/linear.py
tnp/data/noise.py
tnp/data/sawtooth.py
tnp/data/synthetic.py
tnp/likelihoods/__init__.py
tnp/likelihoods/base.py
tnp/likelihoods/gaussian.py
tnp/models/__init__.py
tnp/models/anp.py
tnp/models/base.py
tnp/models/cnp.py
tnp/models/convcnp.py
tnp/models/pttnp.py
tnp/models/tnp.py
tnp/networks/__init__.py
tnp/networks/attention.py
tnp/networks/attention_layers.py
tnp/networks/cnn.py
tnp/networks/deepset.py
tnp/networks/kernels.py
tnp/networks/mlp.py
tnp/networks/setconv.py
tnp/networks/transformer.py
tnp/utils/__init__.py
tnp/utils/batch.py
tnp/utils/experiment_utils.py
tnp/utils/helpers.py
tnp/utils/initialisation.py
tnp/utils/lightning_utils.py
tnpml-0.0.1.dist-info/LICENSE
tnpml-0.0.1.dist-info/METADATA
tnpml-0.0.1.dist-info/WHEEL
tnpml-0.0.1.dist-info/top_level.txt
tnpml-0.0.1.dist-info/RECORD
