Metadata-Version: 2.1
Name: tnpml
Version: 0.0.1
Summary: Transformer neural processes
Author: Matthew Ashman
Author-email: Matthew Ashman <mca39@cam.ac.uk>
Project-URL: Homepage, https://github.com/cambridge-mlg/tnp
Classifier: Programming Language :: Python :: 3
Classifier: License :: OSI Approved :: MIT License
Classifier: Operating System :: OS Independent
Requires-Python: >=3.8
License-File: LICENSE
